README.md
setup.py
seven_wxapp_zxchj/__init__.py
seven_wxapp_zxchj/route.py
seven_wxapp_zxchj.egg-info/PKG-INFO
seven_wxapp_zxchj.egg-info/SOURCES.txt
seven_wxapp_zxchj.egg-info/dependency_links.txt
seven_wxapp_zxchj.egg-info/requires.txt
seven_wxapp_zxchj.egg-info/top_level.txt
seven_wxapp_zxchj/handlers/__init__.py
seven_wxapp_zxchj/handlers/buy_order.py
seven_wxapp_zxchj/handlers/coin.py
seven_wxapp_zxchj/handlers/coupon.py
seven_wxapp_zxchj/handlers/exchange_order.py
seven_wxapp_zxchj/handlers/home_page.py
seven_wxapp_zxchj/handlers/lottery.py
seven_wxapp_zxchj/handlers/machine.py
seven_wxapp_zxchj/handlers/pay.py
seven_wxapp_zxchj/handlers/prize_order.py
seven_wxapp_zxchj/handlers/task.py
seven_wxapp_zxchj/handlers/user.py
seven_wxapp_zxchj/handlers/base/__init__.py
seven_wxapp_zxchj/handlers/base/core_base.py
seven_wxapp_zxchj/models/__init__.py
seven_wxapp_zxchj/models/enum.py
seven_wxapp_zxchj/models/ex_model.py
seven_wxapp_zxchj/models/seven_model.py
seven_wxapp_zxchj/models/db_models/__init__.py
seven_wxapp_zxchj/models/db_models/act/__init__.py
seven_wxapp_zxchj/models/db_models/act/act_info_model.py
seven_wxapp_zxchj/models/db_models/behavior/__init__.py
seven_wxapp_zxchj/models/db_models/behavior/behavior_log_model.py
seven_wxapp_zxchj/models/db_models/behavior/behavior_orm_model.py
seven_wxapp_zxchj/models/db_models/behavior/behavior_report_model.py
seven_wxapp_zxchj/models/db_models/buy/__init__.py
seven_wxapp_zxchj/models/db_models/buy/buy_order_model.py
seven_wxapp_zxchj/models/db_models/carousel/__init__.py
seven_wxapp_zxchj/models/db_models/carousel/carousel_map_model.py
seven_wxapp_zxchj/models/db_models/coin/__init__.py
seven_wxapp_zxchj/models/db_models/coin/coin_exchange_model.py
seven_wxapp_zxchj/models/db_models/coin/coin_record_model.py
seven_wxapp_zxchj/models/db_models/copywriting/__init__.py
seven_wxapp_zxchj/models/db_models/copywriting/copywriting_config_model.py
seven_wxapp_zxchj/models/db_models/coupon/__init__.py
seven_wxapp_zxchj/models/db_models/coupon/coupon_info_model.py
seven_wxapp_zxchj/models/db_models/coupon/coupon_machine_model.py
seven_wxapp_zxchj/models/db_models/exchange/__init__.py
